spefit/__init__.py
spefit/cost.py
spefit/dataset.py
spefit/estimate.py
spefit/fitter.py
spefit/common/__init__.py
spefit/common/basic.py
spefit/common/stats.py
spefit/pdf/__init__.py
spefit/pdf/base.py
spefit/pdf/pmt_single_gaussian.py
spefit/pdf/sipm_gentile.py
spefit/pdf/sipm_geometric.py
spefit/pdf/sipm_modified_poisson.py
spefit-3.0.0.dist-info/LICENSE
spefit-3.0.0.dist-info/METADATA
spefit-3.0.0.dist-info/WHEEL
spefit-3.0.0.dist-info/top_level.txt
spefit-3.0.0.dist-info/RECORD
