Metadata-Version: 2.1
Name: spefit
Version: 3.0.0
Summary: Fitting of Single Photoelectron Spectra.
Author-email: Jason Watson <jason.watson@desy.de>
License: BSD 3-Clause License
Project-URL: Homepage, https://gitlab.cta-observatory.org/cta-consortium/aswg/tools/spefit
Classifier: License :: OSI Approved :: BSD License
Classifier: Programming Language :: Python
Classifier: Programming Language :: Python :: 3
Requires-Python: >=3.9
License-File: LICENSE
Requires-Dist: numpy ~=1.20
Requires-Dist: scipy ~=1.11
Requires-Dist: matplotlib ~=3.7
Requires-Dist: tqdm ~=4.66
Requires-Dist: numba ~=0.57
Requires-Dist: iminuit ~=2.24
Provides-Extra: test
Requires-Dist: black ~=23.9 ; extra == 'test'
Requires-Dist: pytest ~=7.1.2 ; extra == 'test'
